<?xml version='1.0' encoding='UTF-8'?><dataSet xmlns="http://dhis2.org/schema/dxf/2.0" code="ObstetricComplicDeliv" id="u4aKpk1mfW8"><periodType>Monthly</periodType><displayName>Obstetric Complications and Deliveries</displayName><version>261</version><dataSetElements><dataSetElement><dataElement id="roGWjYfjXli"><displayName>Newborns  who did not cry at birth</displayName><valueType>NUMBER</valueType><categoryCombo id="e1sXdbpUsU7"><categoryOptionCombos><categoryOptionCombo name="default" id="BNTdWBe0N1F"><categoryOptions><categoryOption name="default"><categories><category name="default"/></categories></categoryOption></categoryOptions></categoryOptionCombo></categoryOptionCombos></categoryCombo></dataElement></dataSetElement><dataSetElement><dataElement id="m9t2NnjUOIV"><displayName>Total number of maternal deaths audited at Community level_ 20 Years and above</displayName><valueType>NUMBER</valueType><categoryCombo id="e1sXdbpUsU7"><categoryOptionCombos><categoryOptionCombo name="default" id="BNTdWBe0N1F"><categoryOptions><categoryOption name="default"><categories><category name="default"/></categories></categoryOption></categoryOptions></categoryOptionCombo></categoryOptionCombos></categoryCombo></dataElement></dataSetElement><dataSetElement><dataElement id="e2sJTz8eoJM"><displayName>Deliveries 15 years and under </displayName><valueType>NUMBER</valueType><categoryCombo id="e1sXdbpUsU7"><categoryOptionCombos><categoryOptionCombo name="default" id="BNTdWBe0N1F"><categoryOptions><categoryOption name="default"><categories><category name="default"/></categories></categoryOption></categoryOptions></categoryOptionCombo></categoryOptionCombos></categoryCombo></dataElement></dataSetElement><dataSetElement><dataElement id="yiqBXJJuu1J"><displayName>Intravenus Antibiotics</displayName><valueType>NUMBER</valueType><categoryCombo id="e1sXdbpUsU7"><categoryOptionCombos><categoryOptionCombo name="default" id="BNTdWBe0N1F"><categoryOptions><categoryOption name="default"><categories><category name="default"/></categories></categoryOption></categoryOptions></categoryOptionCombo></categoryOptionCombos></categoryCombo></dataElement></dataSetElement><dataSetElement><dataElement id="IxW5HShSqL0"><displayName>Anemia Severe _&lt;7gm/dl_Deaths</displayName><valueType>NUMBER</valueType><categoryCombo id="ygwDvwJSrQe"><categoryOptionCombos><categoryOptionCombo name="20yrs and above" id="aHaDmg73rhA"><categoryOptions><categoryOption name="20yrs and above"><categories><category name="Obstetric age group"/></categories></categoryOption></categoryOptions></categoryOptionCombo><categoryOptionCombo name="Under 20yrs" id="n0DeQmJ9EVJ"><categoryOptions><categoryOption name="Under 20yrs"><categories><category name="Obstetric age group"/></categories></categoryOption></categoryOptions></categoryOptionCombo></categoryOptionCombos></categoryCombo></dataElement></dataSetElement><dataSetElement><dataElement id="finJo7dbcyC"><displayName>Eclampsia  or Severe Pre_Eclampsia _Death</displayName><valueType>NUMBER</valueType><categoryCombo id="ygwDvwJSrQe"><categoryOptionCombos><categoryOptionCombo name="20yrs and above" id="aHaDmg73rhA"><categoryOptions><categoryOption name="20yrs and above"><categories><category name="Obstetric age group"/></categories></categoryOption></categoryOptions></categoryOptionCombo><categoryOptionCombo name="Under 20yrs" id="n0DeQmJ9EVJ"><categoryOptions><categoryOption name="Under 20yrs"><categories><category name="Obstetric age group"/></categories></categoryOption></categoryOptions></categoryOptionCombo></categoryOptionCombos></categoryCombo></dataElement></dataSetElement><dataSetElement><dataElement id="iVqhgMJDG2E"><displayName>Sepsis_Postpartum infection_OPDNC</displayName><valueType>NUMBER</valueType><categoryCombo id="ygwDvwJSrQe"><categoryOptionCombos><categoryOptionCombo name="20yrs and above" id="aHaDmg73rhA"><categoryOptions><categoryOption name="20yrs and above"><categories><category name="Obstetric age group"/></categories></categoryOption></categoryOptions></categoryOptionCombo><categoryOptionCombo name="Under 20yrs" id="n0DeQmJ9EVJ"><categoryOptions><categoryOption name="Under 20yrs"><categories><category name="Obstetric age group"/></categories></categoryOption></categoryOptions></categoryOptionCombo></categoryOptionCombos></categoryCombo></dataElement></dataSetElement><dataSetElement><dataElement id="FhnChCIJkGC"><displayName>Sepsis_Postpartum infection_Deaths</displayName><valueType>NUMBER</valueType><categoryCombo id="ygwDvwJSrQe"><categoryOptionCombos><categoryOptionCombo name="20yrs and above" id="aHaDmg73rhA"><categoryOptions><categoryOption name="20yrs and above"><categories><category name="Obstetric age group"/></categories></categoryOption></categoryOptions></categoryOptionCombo><categoryOptionCombo name="Under 20yrs" id="n0DeQmJ9EVJ"><categoryOptions><categoryOption name="Under 20yrs"><categories><category name="Obstetric age group"/></categories></categoryOption></categoryOptions></categoryOptionCombo></categoryOptionCombos></categoryCombo></dataElement></dataSetElement><dataSetElement><dataElement id="ubvZdbfmOfL"><displayName>Obstetrical Complication Other_HOSP</displayName><valueType>NUMBER</valueType><categoryCombo id="ygwDvwJSrQe"><categoryOptionCombos><categoryOptionCombo name="20yrs and above" id="aHaDmg73rhA"><categoryOptions><categoryOption name="20yrs and above"><categories><category name="Obstetric age group"/></categories></categoryOption></categoryOptions></categoryOptionCombo><categoryOptionCombo name="Under 20yrs" id="n0DeQmJ9EVJ"><categoryOptions><categoryOption name="Under 20yrs"><categories><category name="Obstetric age group"/></categories></categoryOption></categoryOptions></categoryOptionCombo></categoryOptionCombos></categoryCombo></dataElement></dataSetElement><dataSetElement><dataElement id="L8Edu8n8siQ"><displayName>Malaria with minor digestive symptoms in pregnancyDeath_Obs</displayName><valueType>NUMBER</valueType><categoryCombo id="ygwDvwJSrQe"><categoryOptionCombos><categoryOptionCombo name="20yrs and above" id="aHaDmg73rhA"><categoryOptions><categoryOption name="20yrs and above"><categories><category name="Obstetric age group"/></categories></categoryOption></categoryOptions></categoryOptionCombo><categoryOptionCombo name="Under 20yrs" id="n0DeQmJ9EVJ"><categoryOptions><categoryOption name="Under 20yrs"><categories><category name="Obstetric age group"/></categories></categoryOption></categoryOptions></categoryOptionCombo></categoryOptionCombos></categoryCombo></dataElement></dataSetElement><dataSetElement><dataElement id="j2prahOx4Hb"><displayName>Premature birth weight &lt;2.5 kg_alive22-37 weeks</displayName><valueType>NUMBER</valueType><categoryCombo id="e1sXdbpUsU7"><categoryOptionCombos><categoryOptionCombo name="default" id="BNTdWBe0N1F"><categoryOptions><categoryOption name="default"><categories><category name="default"/></categories></categoryOption></categoryOptions></categoryOptionCombo></categoryOptionCombos></categoryCombo></dataElement></dataSetElement><dataSetElement><dataElement id="W6xwcqzSy5P"><displayName>Antepartum Haemorrhage_Deaths</displayName><valueType>NUMBER</valueType><categoryCombo id="ygwDvwJSrQe"><categoryOptionCombos><categoryOptionCombo name="20yrs and above" id="aHaDmg73rhA"><categoryOptions><categoryOption name="20yrs and above"><categories><category name="Obstetric age group"/></categories></categoryOption></categoryOptions></categoryOptionCombo><categoryOptionCombo name="Under 20yrs" id="n0DeQmJ9EVJ"><categoryOptions><categoryOption name="Under 20yrs"><categories><category name="Obstetric age group"/></categories></categoryOption></categoryOptions></categoryOptionCombo></categoryOptionCombos></categoryCombo></dataElement></dataSetElement><dataSetElement><dataElement id="ya7qr3mLlW0"><displayName>Death at birth</displayName><valueType>NUMBER</valueType><categoryCombo id="e1sXdbpUsU7"><categoryOptionCombos><categoryOptionCombo name="default" id="BNTdWBe0N1F"><categoryOptions><categoryOption name="default"><categories><category name="default"/></categories></categoryOption></categoryOptions></categoryOptionCombo></categoryOptionCombos></categoryCombo></dataElement></dataSetElement><dataSetElement><dataElement id="By6864mI9q5"><displayName>Total number of maternal deaths audited at Community level_ under 20 Years</displayName><valueType>NUMBER</valueType><categoryCombo id="e1sXdbpUsU7"><categoryOptionCombos><categoryOptionCombo name="default" id="BNTdWBe0N1F"><categoryOptions><categoryOption name="default"><categories><category name="default"/></categories></categoryOption></categoryOptions></categoryOptionCombo></categoryOptionCombos></categoryCombo></dataElement></dataSetElement><dataSetElement><dataElement id="ivMl0IeZoAX"><displayName>Women accompanied or referred by CHW to HC for assisted deliveries</displayName><valueType>NUMBER</valueType><categoryCombo id="e1sXdbpUsU7"><categoryOptionCombos><categoryOptionCombo name="default" id="BNTdWBe0N1F"><categoryOptions><categoryOption name="default"><categories><category name="default"/></categories></categoryOption></categoryOptions></categoryOptionCombo></categoryOptionCombos></categoryCombo></dataElement></dataSetElement><dataSetElement><dataElement id="iUwlocA4KI9"><displayName>Fistula_vesico vaginal or rectal_Deaths</displayName><valueType>NUMBER</valueType><categoryCombo id="ygwDvwJSrQe"><categoryOptionCombos><categoryOptionCombo name="20yrs and above" id="aHaDmg73rhA"><categoryOptions><categoryOption name="20yrs and above"><categories><category name="Obstetric age group"/></categories></categoryOption></categoryOptions></categoryOptionCombo><categoryOptionCombo name="Under 20yrs" id="n0DeQmJ9EVJ"><categoryOptions><categoryOption name="Under 20yrs"><categories><category name="Obstetric age group"/></categories></categoryOption></categoryOptions></categoryOptionCombo></categoryOptionCombos></categoryCombo></dataElement></dataSetElement><dataSetElement><dataElement id="V37PdjvVf01"><displayName>Perineal tear 3rd Degree_OPDNC</displayName><valueType>NUMBER</valueType><categoryCombo id="ygwDvwJSrQe"><categoryOptionCombos><categoryOptionCombo name="20yrs and above" id="aHaDmg73rhA"><categoryOptions><categoryOption name="20yrs and above"><categories><category name="Obstetric age group"/></categories></categoryOption></categoryOptions></categoryOptionCombo><categoryOptionCombo name="Under 20yrs" id="n0DeQmJ9EVJ"><categoryOptions><categoryOption name="Under 20yrs"><categories><category name="Obstetric age group"/></categories></categoryOption></categoryOptions></categoryOptionCombo></categoryOptionCombos></categoryCombo></dataElement></dataSetElement><dataSetElement><dataElement id="DnekMOdY0YJ"><displayName>Manual removal of placenta</displayName><valueType>NUMBER</valueType><categoryCombo id="e1sXdbpUsU7"><categoryOptionCombos><categoryOptionCombo name="default" id="BNTdWBe0N1F"><categoryOptions><categoryOption name="default"><categories><category name="default"/></categories></categoryOption></categoryOptions></categoryOptionCombo></categoryOptionCombos></categoryCombo></dataElement></dataSetElement><dataSetElement><dataElement id="yNbxJhcQAjN"><displayName>HIV/Opportunistic Infections_Death</displayName><valueType>NUMBER</valueType><categoryCombo id="ygwDvwJSrQe"><categoryOptionCombos><categoryOptionCombo name="20yrs and above" id="aHaDmg73rhA"><categoryOptions><categoryOption name="20yrs and above"><categories><category name="Obstetric age group"/></categories></categoryOption></categoryOptions></categoryOptionCombo><categoryOptionCombo name="Under 20yrs" id="n0DeQmJ9EVJ"><categoryOptions><categoryOption name="Under 20yrs"><categories><category name="Obstetric age group"/></categories></categoryOption></categoryOptions></categoryOptionCombo></categoryOptionCombos></categoryCombo></dataElement></dataSetElement><dataSetElement><dataElement id="UGbGaasQaMZ"><displayName>Death 0-7 days (excl. death at birth)</displayName><valueType>NUMBER</valueType><categoryCombo id="e1sXdbpUsU7"><categoryOptionCombos><categoryOptionCombo name="default" id="BNTdWBe0N1F"><categoryOptions><categoryOption name="default"><categories><category name="default"/></categories></categoryOption></categoryOptions></categoryOptionCombo></categoryOptionCombos></categoryCombo></dataElement></dataSetElement><dataSetElement><dataElement id="GUFOag9rDN1"><displayName>Foetal Distress_Deaths</displayName><valueType>NUMBER</valueType><categoryCombo id="ygwDvwJSrQe"><categoryOptionCombos><categoryOptionCombo name="20yrs and above" id="aHaDmg73rhA"><categoryOptions><categoryOption name="20yrs and above"><categories><category name="Obstetric age group"/></categories></categoryOption></categoryOptions></categoryOptionCombo><categoryOptionCombo name="Under 20yrs" id="n0DeQmJ9EVJ"><categoryOptions><categoryOption name="Under 20yrs"><categories><category name="Obstetric age group"/></categories></categoryOption></categoryOptions></categoryOptionCombo></categoryOptionCombos></categoryCombo></dataElement></dataSetElement><dataSetElement><dataElement id="DO1JSzDD2mN"><displayName>Prolonged or Obstructed labor_OPDNC</displayName><valueType>NUMBER</valueType><categoryCombo id="ygwDvwJSrQe"><categoryOptionCombos><categoryOptionCombo name="20yrs and above" id="aHaDmg73rhA"><categoryOptions><categoryOption name="20yrs and above"><categories><category name="Obstetric age group"/></categories></categoryOption></categoryOptions></categoryOptionCombo><categoryOptionCombo name="Under 20yrs" id="n0DeQmJ9EVJ"><categoryOptions><categoryOption name="Under 20yrs"><categories><category name="Obstetric age group"/></categories></categoryOption></categoryOptions></categoryOptionCombo></categoryOptionCombos></categoryCombo></dataElement></dataSetElement><dataSetElement><dataElement id="vopAfAvKOvG"><displayName>Post-partum hemorrhage_Hosp</displayName><valueType>NUMBER</valueType><categoryCombo id="ygwDvwJSrQe"><categoryOptionCombos><categoryOptionCombo name="20yrs and above" id="aHaDmg73rhA"><categoryOptions><categoryOption name="20yrs and above"><categories><category name="Obstetric age group"/></categories></categoryOption></categoryOptions></categoryOptionCombo><categoryOptionCombo name="Under 20yrs" id="n0DeQmJ9EVJ"><categoryOptions><categoryOption name="Under 20yrs"><categories><category name="Obstetric age group"/></categories></categoryOption></categoryOptions></categoryOptionCombo></categoryOptionCombos></categoryCombo></dataElement></dataSetElement><dataSetElement><dataElement id="imarVkOVmJi"><displayName>Miscarriages_spontaneous abortions_Hosp</displayName><valueType>NUMBER</valueType><categoryCombo id="ygwDvwJSrQe"><categoryOptionCombos><categoryOptionCombo name="20yrs and above" id="aHaDmg73rhA"><categoryOptions><categoryOption name="20yrs and above"><categories><category name="Obstetric age group"/></categories></categoryOption></categoryOptions></categoryOptionCombo><categoryOptionCombo name="Under 20yrs" id="n0DeQmJ9EVJ"><categoryOptions><categoryOption name="Under 20yrs"><categories><category name="Obstetric age group"/></categories></categoryOption></categoryOptions></categoryOptionCombo></categoryOptionCombos></categoryCombo></dataElement></dataSetElement><dataSetElement><dataElement id="XFojeeVFG4y"><displayName>Newborns resuscitated</displayName><valueType>NUMBER</valueType><categoryCombo id="e1sXdbpUsU7"><categoryOptionCombos><categoryOptionCombo name="default" id="BNTdWBe0N1F"><categoryOptions><categoryOption name="default"><categories><category name="default"/></categories></categoryOption></categoryOptions></categoryOptionCombo></categoryOptionCombos></categoryCombo></dataElement></dataSetElement><dataSetElement><dataElement id="zzu1At9VFrE"><displayName>Cleft palette_deliveries</displayName><valueType>NUMBER</valueType><categoryCombo id="e1sXdbpUsU7"><categoryOptionCombos><categoryOptionCombo name="default" id="BNTdWBe0N1F"><categoryOptions><categoryOption name="default"><categories><category name="default"/></categories></categoryOption></categoryOptions></categoryOptionCombo></categoryOptionCombos></categoryCombo></dataElement></dataSetElement><dataSetElement><dataElement id="vyNCXGQT3bn"><displayName>Post-partum hemorrhage_Deaths</displayName><valueType>NUMBER</valueType><categoryCombo id="ygwDvwJSrQe"><categoryOptionCombos><categoryOptionCombo name="20yrs and above" id="aHaDmg73rhA"><categoryOptions><categoryOption name="20yrs and above"><categories><category name="Obstetric age group"/></categories></categoryOption></categoryOptions></categoryOptionCombo><categoryOptionCombo name="Under 20yrs" id="n0DeQmJ9EVJ"><categoryOptions><categoryOption name="Under 20yrs"><categories><category name="Obstetric age group"/></categories></categoryOption></categoryOptions></categoryOptionCombo></categoryOptionCombos></categoryCombo></dataElement></dataSetElement><dataSetElement><dataElement id="ztFTEpPnkNL"><displayName>Abortions_symptoms suggesting induced abortionDeaths</displayName><valueType>NUMBER</valueType><categoryCombo id="ygwDvwJSrQe"><categoryOptionCombos><categoryOptionCombo name="20yrs and above" id="aHaDmg73rhA"><categoryOptions><categoryOption name="20yrs and above"><categories><category name="Obstetric age group"/></categories></categoryOption></categoryOptions></categoryOptionCombo><categoryOptionCombo name="Under 20yrs" id="n0DeQmJ9EVJ"><categoryOptions><categoryOption name="Under 20yrs"><categories><category name="Obstetric age group"/></categories></categoryOption></categoryOptions></categoryOptionCombo></categoryOptionCombos></categoryCombo></dataElement></dataSetElement><dataSetElement><dataElement id="YNKAG92cvSS"><displayName>HIV/Opportunistic Infections_Hosp</displayName><valueType>NUMBER</valueType><categoryCombo id="ygwDvwJSrQe"><categoryOptionCombos><categoryOptionCombo name="20yrs and above" id="aHaDmg73rhA"><categoryOptions><categoryOption name="20yrs and above"><categories><category name="Obstetric age group"/></categories></categoryOption></categoryOptions></categoryOptionCombo><categoryOptionCombo name="Under 20yrs" id="n0DeQmJ9EVJ"><categoryOptions><categoryOption name="Under 20yrs"><categories><category name="Obstetric age group"/></categories></categoryOption></categoryOptions></categoryOptionCombo></categoryOptionCombos></categoryCombo></dataElement></dataSetElement><dataSetElement><dataElement id="FlkG7IvO2W7"><displayName>Perineal tear 3rd Degree_Hosp</displayName><valueType>NUMBER</valueType><categoryCombo id="ygwDvwJSrQe"><categoryOptionCombos><categoryOptionCombo name="20yrs and above" id="aHaDmg73rhA"><categoryOptions><categoryOption name="20yrs and above"><categories><category name="Obstetric age group"/></categories></categoryOption></categoryOptions></categoryOptionCombo><categoryOptionCombo name="Under 20yrs" id="n0DeQmJ9EVJ"><categoryOptions><categoryOption name="Under 20yrs"><categories><category name="Obstetric age group"/></categories></categoryOption></categoryOptions></categoryOptionCombo></categoryOptionCombos></categoryCombo></dataElement></dataSetElement><dataSetElement><dataElement id="xBj1LvlyUig"><displayName>Death 8 to 28 days</displayName><valueType>NUMBER</valueType><categoryCombo id="e1sXdbpUsU7"><categoryOptionCombos><categoryOptionCombo name="default" id="BNTdWBe0N1F"><categoryOptions><categoryOption name="default"><categories><category name="default"/></categories></categoryOption></categoryOptions></categoryOptionCombo></categoryOptionCombos></categoryCombo></dataElement></dataSetElement><dataSetElement><dataElement id="lgmE4mlzlky"><displayName>Foetal Distress_Hosp</displayName><valueType>NUMBER</valueType><categoryCombo id="ygwDvwJSrQe"><categoryOptionCombos><categoryOptionCombo name="20yrs and above" id="aHaDmg73rhA"><categoryOptions><categoryOption name="20yrs and above"><categories><category name="Obstetric age group"/></categories></categoryOption></categoryOptions></categoryOptionCombo><categoryOptionCombo name="Under 20yrs" id="n0DeQmJ9EVJ"><categoryOptions><categoryOption name="Under 20yrs"><categories><category name="Obstetric age group"/></categories></categoryOption></categoryOptions></categoryOptionCombo></categoryOptionCombos></categoryCombo></dataElement></dataSetElement><dataSetElement><dataElement id="MdXuj2ZVxYU"><displayName>Malaria simple in pregnancyDeath_Obs</displayName><valueType>NUMBER</valueType><categoryCombo id="ygwDvwJSrQe"><categoryOptionCombos><categoryOptionCombo name="20yrs and above" id="aHaDmg73rhA"><categoryOptions><categoryOption name="20yrs and above"><categories><category name="Obstetric age group"/></categories></categoryOption></categoryOptions></categoryOptionCombo><categoryOptionCombo name="Under 20yrs" id="n0DeQmJ9EVJ"><categoryOptions><categoryOption name="Under 20yrs"><categories><category name="Obstetric age group"/></categories></categoryOption></categoryOptions></categoryOptionCombo></categoryOptionCombos></categoryCombo></dataElement></dataSetElement><dataSetElement><dataElement id="XYHy7efMtNg"><displayName>Vacuum extraction</displayName><valueType>NUMBER</valueType><categoryCombo id="e1sXdbpUsU7"><categoryOptionCombos><categoryOptionCombo name="default" id="BNTdWBe0N1F"><categoryOptions><categoryOption name="default"><categories><category name="default"/></categories></categoryOption></categoryOptions></categoryOptionCombo></categoryOptionCombos></categoryCombo></dataElement></dataSetElement><dataSetElement><dataElement id="av7esaF3e2R"><displayName>Anemia Severe _&lt;7gm/dl_OPDNC</displayName><valueType>NUMBER</valueType><categoryCombo id="ygwDvwJSrQe"><categoryOptionCombos><categoryOptionCombo name="20yrs and above" id="aHaDmg73rhA"><categoryOptions><categoryOption name="20yrs and above"><categories><category name="Obstetric age group"/></categories></categoryOption></categoryOptions></categoryOptionCombo><categoryOptionCombo name="Under 20yrs" id="n0DeQmJ9EVJ"><categoryOptions><categoryOption name="Under 20yrs"><categories><category name="Obstetric age group"/></categories></categoryOption></categoryOptions></categoryOptionCombo></categoryOptionCombos></categoryCombo></dataElement></dataSetElement><dataSetElement><dataElement id="uvSKt0o9N28"><displayName>Newborns who did not cry at birth and were resuscitated</displayName><valueType>NUMBER</valueType><categoryCombo id="e1sXdbpUsU7"><categoryOptionCombos><categoryOptionCombo name="default" id="BNTdWBe0N1F"><categoryOptions><categoryOption name="default"><categories><category name="default"/></categories></categoryOption></categoryOptions></categoryOptionCombo></categoryOptionCombos></categoryCombo></dataElement></dataSetElement><dataSetElement><dataElement id="STB1UVUaouP"><displayName>Ectopic pregnancy_Hospitalized</displayName><valueType>NUMBER</valueType><categoryCombo id="ygwDvwJSrQe"><categoryOptionCombos><categoryOptionCombo name="20yrs and above" id="aHaDmg73rhA"><categoryOptions><categoryOption name="20yrs and above"><categories><category name="Obstetric age group"/></categories></categoryOption></categoryOptions></categoryOptionCombo><categoryOptionCombo name="Under 20yrs" id="n0DeQmJ9EVJ"><categoryOptions><categoryOption name="Under 20yrs"><categories><category name="Obstetric age group"/></categories></categoryOption></categoryOptions></categoryOptionCombo></categoryOptionCombos></categoryCombo></dataElement></dataSetElement><dataSetElement><dataElement id="N2dP088PmPy"><displayName>Malaria confirmed_Hosp</displayName><valueType>NUMBER</valueType><categoryCombo id="ygwDvwJSrQe"><categoryOptionCombos><categoryOptionCombo name="20yrs and above" id="aHaDmg73rhA"><categoryOptions><categoryOption name="20yrs and above"><categories><category name="Obstetric age group"/></categories></categoryOption></categoryOptions></categoryOptionCombo><categoryOptionCombo name="Under 20yrs" id="n0DeQmJ9EVJ"><categoryOptions><categoryOption name="Under 20yrs"><categories><category name="Obstetric age group"/></categories></categoryOption></categoryOptions></categoryOptionCombo></categoryOptionCombos></categoryCombo></dataElement></dataSetElement><dataSetElement><dataElement id="BLuz04BPsyk"><displayName>Obstetrical complications other_Hosp_obs</displayName><valueType>NUMBER</valueType><categoryCombo id="ygwDvwJSrQe"><categoryOptionCombos><categoryOptionCombo name="20yrs and above" id="aHaDmg73rhA"><categoryOptions><categoryOption name="20yrs and above"><categories><category name="Obstetric age group"/></categories></categoryOption></categoryOptions></categoryOptionCombo><categoryOptionCombo name="Under 20yrs" id="n0DeQmJ9EVJ"><categoryOptions><categoryOption name="Under 20yrs"><categories><category name="Obstetric age group"/></categories></categoryOption></categoryOptions></categoryOptionCombo></categoryOptionCombos></categoryCombo></dataElement></dataSetElement><dataSetElement><dataElement id="OhfS6PR4vH1"><displayName>Uterine rupture or tear_OPDNC</displayName><valueType>NUMBER</valueType><categoryCombo id="ygwDvwJSrQe"><categoryOptionCombos><categoryOptionCombo name="20yrs and above" id="aHaDmg73rhA"><categoryOptions><categoryOption name="20yrs and above"><categories><category name="Obstetric age group"/></categories></categoryOption></categoryOptions></categoryOptionCombo><categoryOptionCombo name="Under 20yrs" id="n0DeQmJ9EVJ"><categoryOptions><categoryOption name="Under 20yrs"><categories><category name="Obstetric age group"/></categories></categoryOption></categoryOptions></categoryOptionCombo></categoryOptionCombos></categoryCombo></dataElement></dataSetElement><dataSetElement><dataElement id="fh2n9ROWVaa"><displayName>Prolonged or Obstructed labor_Deaths</displayName><valueType>NUMBER</valueType><categoryCombo id="ygwDvwJSrQe"><categoryOptionCombos><categoryOptionCombo name="20yrs and above" id="aHaDmg73rhA"><categoryOptions><categoryOption name="20yrs and above"><categories><category name="Obstetric age group"/></categories></categoryOption></categoryOptions></categoryOptionCombo><categoryOptionCombo name="Under 20yrs" id="n0DeQmJ9EVJ"><categoryOptions><categoryOption name="Under 20yrs"><categories><category name="Obstetric age group"/></categories></categoryOption></categoryOptions></categoryOptionCombo></categoryOptionCombos></categoryCombo></dataElement></dataSetElement><dataSetElement><dataElement id="PdDHrFyFqiG"><displayName>Fistula_vesico vaginal or rectal_OPDNC</displayName><valueType>NUMBER</valueType><categoryCombo id="ygwDvwJSrQe"><categoryOptionCombos><categoryOptionCombo name="20yrs and above" id="aHaDmg73rhA"><categoryOptions><categoryOption name="20yrs and above"><categories><category name="Obstetric age group"/></categories></categoryOption></categoryOptions></categoryOptionCombo><categoryOptionCombo name="Under 20yrs" id="n0DeQmJ9EVJ"><categoryOptions><categoryOption name="Under 20yrs"><categories><category name="Obstetric age group"/></categories></categoryOption></categoryOptions></categoryOptionCombo></categoryOptionCombos></categoryCombo></dataElement></dataSetElement><dataSetElement><dataElement id="zaOxK9xOxcv"><displayName>Deliveries abnormal_dystocic</displayName><valueType>NUMBER</valueType><categoryCombo id="e1sXdbpUsU7"><categoryOptionCombos><categoryOptionCombo name="default" id="BNTdWBe0N1F"><categoryOptions><categoryOption name="default"><categories><category name="default"/></categories></categoryOption></categoryOptions></categoryOptionCombo></categoryOptionCombos></categoryCombo></dataElement></dataSetElement><dataSetElement><dataElement id="t3GLvTvbekD"><displayName>Newborns resuscitated successfully_cry within 5 minutes</displayName><valueType>NUMBER</valueType><categoryCombo id="e1sXdbpUsU7"><categoryOptionCombos><categoryOptionCombo name="default" id="BNTdWBe0N1F"><categoryOptions><categoryOption name="default"><categories><category name="default"/></categories></categoryOption></categoryOptions></categoryOptionCombo></categoryOptionCombos></categoryCombo></dataElement></dataSetElement><dataSetElement><dataElement id="YxD30b7kSAo"><displayName>Deliveries normal</displayName><valueType>NUMBER</valueType><categoryCombo id="e1sXdbpUsU7"><categoryOptionCombos><categoryOptionCombo name="default" id="BNTdWBe0N1F"><categoryOptions><categoryOption name="default"><categories><category name="default"/></categories></categoryOption></categoryOptions></categoryOptionCombo></categoryOptionCombos></categoryCombo></dataElement></dataSetElement><dataSetElement><dataElement id="VrD6MfV2nqL"><displayName>Malaria simple in pregnancyOPDNC_Obs</displayName><valueType>NUMBER</valueType><categoryCombo id="ygwDvwJSrQe"><categoryOptionCombos><categoryOptionCombo name="20yrs and above" id="aHaDmg73rhA"><categoryOptions><categoryOption name="20yrs and above"><categories><category name="Obstetric age group"/></categories></categoryOption></categoryOptions></categoryOptionCombo><categoryOptionCombo name="Under 20yrs" id="n0DeQmJ9EVJ"><categoryOptions><categoryOption name="Under 20yrs"><categories><category name="Obstetric age group"/></categories></categoryOption></categoryOptions></categoryOptionCombo></categoryOptionCombos></categoryCombo></dataElement></dataSetElement><dataSetElement><dataElement id="QEjTEBB9ILB"><displayName>Obstetrical Complications Other_OPDNC</displayName><valueType>NUMBER</valueType><categoryCombo id="ygwDvwJSrQe"><categoryOptionCombos><categoryOptionCombo name="20yrs and above" id="aHaDmg73rhA"><categoryOptions><categoryOption name="20yrs and above"><categories><category name="Obstetric age group"/></categories></categoryOption></categoryOptions></categoryOptionCombo><categoryOptionCombo name="Under 20yrs" id="n0DeQmJ9EVJ"><categoryOptions><categoryOption name="Under 20yrs"><categories><category name="Obstetric age group"/></categories></categoryOption></categoryOptions></categoryOptionCombo></categoryOptionCombos></categoryCombo></dataElement></dataSetElement><dataSetElement><dataElement id="MUVy3vnpg6n"><displayName>Perineal tear 3rd Degree_Deaths</displayName><valueType>NUMBER</valueType><categoryCombo id="ygwDvwJSrQe"><categoryOptionCombos><categoryOptionCombo name="20yrs and above" id="aHaDmg73rhA"><categoryOptions><categoryOption name="20yrs and above"><categories><category name="Obstetric age group"/></categories></categoryOption></categoryOptions></categoryOptionCombo><categoryOptionCombo name="Under 20yrs" id="n0DeQmJ9EVJ"><categoryOptions><categoryOption name="Under 20yrs"><categories><category name="Obstetric age group"/></categories></categoryOption></categoryOptions></categoryOptionCombo></categoryOptionCombos></categoryCombo></dataElement></dataSetElement><dataSetElement><dataElement id="gTNHPjt1scq"><displayName>Malaria with minor digestive symptoms in pregnancyHosp_Obs</displayName><valueType>NUMBER</valueType><categoryCombo id="ygwDvwJSrQe"><categoryOptionCombos><categoryOptionCombo name="20yrs and above" id="aHaDmg73rhA"><categoryOptions><categoryOption name="20yrs and above"><categories><category name="Obstetric age group"/></categories></categoryOption></categoryOptions></categoryOptionCombo><categoryOptionCombo name="Under 20yrs" id="n0DeQmJ9EVJ"><categoryOptions><categoryOption name="Under 20yrs"><categories><category name="Obstetric age group"/></categories></categoryOption></categoryOptions></categoryOptionCombo></categoryOptionCombos></categoryCombo></dataElement></dataSetElement><dataSetElement><dataElement id="rxUPenL7Kjk"><displayName>Eclampsia  or Severe Pre_Eclampsia_OPDNC </displayName><valueType>NUMBER</valueType><categoryCombo id="ygwDvwJSrQe"><categoryOptionCombos><categoryOptionCombo name="20yrs and above" id="aHaDmg73rhA"><categoryOptions><categoryOption name="20yrs and above"><categories><category name="Obstetric age group"/></categories></categoryOption></categoryOptions></categoryOptionCombo><categoryOptionCombo name="Under 20yrs" id="n0DeQmJ9EVJ"><categoryOptions><categoryOption name="Under 20yrs"><categories><category name="Obstetric age group"/></categories></categoryOption></categoryOptions></categoryOptionCombo></categoryOptionCombos></categoryCombo></dataElement></dataSetElement><dataSetElement><dataElement id="E80E6J5edUi"><displayName>Miscarriages_spontaneous abortions_Deaths</displayName><valueType>NUMBER</valueType><categoryCombo id="ygwDvwJSrQe"><categoryOptionCombos><categoryOptionCombo name="20yrs and above" id="aHaDmg73rhA"><categoryOptions><categoryOption name="20yrs and above"><categories><category name="Obstetric age group"/></categories></categoryOption></categoryOptions></categoryOptionCombo><categoryOptionCombo name="Under 20yrs" id="n0DeQmJ9EVJ"><categoryOptions><categoryOption name="Under 20yrs"><categories><category name="Obstetric age group"/></categories></categoryOption></categoryOptions></categoryOptionCombo></categoryOptionCombos></categoryCombo></dataElement></dataSetElement><dataSetElement><dataElement id="ssBIvkQoLWl"><displayName>Threat of premature delivery_OPDNC</displayName><valueType>NUMBER</valueType><categoryCombo id="ygwDvwJSrQe"><categoryOptionCombos><categoryOptionCombo name="20yrs and above" id="aHaDmg73rhA"><categoryOptions><categoryOption name="20yrs and above"><categories><category name="Obstetric age group"/></categories></categoryOption></categoryOptions></categoryOptionCombo><categoryOptionCombo name="Under 20yrs" id="n0DeQmJ9EVJ"><categoryOptions><categoryOption name="Under 20yrs"><categories><category name="Obstetric age group"/></categories></categoryOption></categoryOptions></categoryOptionCombo></categoryOptionCombos></categoryCombo></dataElement></dataSetElement><dataSetElement><dataElement id="xWFZ9qBht5d"><displayName>Eclampsia  or Severe Pre_Eclampsia_Hosp</displayName><valueType>NUMBER</valueType><categoryCombo id="ygwDvwJSrQe"><categoryOptionCombos><categoryOptionCombo name="20yrs and above" id="aHaDmg73rhA"><categoryOptions><categoryOption name="20yrs and above"><categories><category name="Obstetric age group"/></categories></categoryOption></categoryOptions></categoryOptionCombo><categoryOptionCombo name="Under 20yrs" id="n0DeQmJ9EVJ"><categoryOptions><categoryOption name="Under 20yrs"><categories><category name="Obstetric age group"/></categories></categoryOption></categoryOptions></categoryOptionCombo></categoryOptionCombos></categoryCombo></dataElement></dataSetElement><dataSetElement><dataElement id="o3WsIFFHqw7"><displayName>Abortions_symptoms suggesting induced abortionHosp</displayName><valueType>NUMBER</valueType><categoryCombo id="ygwDvwJSrQe"><categoryOptionCombos><categoryOptionCombo name="20yrs and above" id="aHaDmg73rhA"><categoryOptions><categoryOption name="20yrs and above"><categories><category name="Obstetric age group"/></categories></categoryOption></categoryOptions></categoryOptionCombo><categoryOptionCombo name="Under 20yrs" id="n0DeQmJ9EVJ"><categoryOptions><categoryOption name="Under 20yrs"><categories><category name="Obstetric age group"/></categories></categoryOption></categoryOptions></categoryOptionCombo></categoryOptionCombos></categoryCombo></dataElement></dataSetElement><dataSetElement><dataElement id="tOtCdCPSeXK"><displayName>Malaria confirmed_OPDNC</displayName><valueType>NUMBER</valueType><categoryCombo id="ygwDvwJSrQe"><categoryOptionCombos><categoryOptionCombo name="20yrs and above" id="aHaDmg73rhA"><categoryOptions><categoryOption name="20yrs and above"><categories><category name="Obstetric age group"/></categories></categoryOption></categoryOptions></categoryOptionCombo><categoryOptionCombo name="Under 20yrs" id="n0DeQmJ9EVJ"><categoryOptions><categoryOption name="Under 20yrs"><categories><category name="Obstetric age group"/></categories></categoryOption></categoryOptions></categoryOptionCombo></categoryOptionCombos></categoryCombo></dataElement></dataSetElement><dataSetElement><dataElement id="zH0Amtv8Mr6"><displayName>Malaria with minor digestive symptoms in pregnancyOPDNC_Obs</displayName><valueType>NUMBER</valueType><categoryCombo id="ygwDvwJSrQe"><categoryOptionCombos><categoryOptionCombo name="20yrs and above" id="aHaDmg73rhA"><categoryOptions><categoryOption name="20yrs and above"><categories><category name="Obstetric age group"/></categories></categoryOption></categoryOptions></categoryOptionCombo><categoryOptionCombo name="Under 20yrs" id="n0DeQmJ9EVJ"><categoryOptions><categoryOption name="Under 20yrs"><categories><category name="Obstetric age group"/></categories></categoryOption></categoryOptions></categoryOptionCombo></categoryOptionCombos></categoryCombo></dataElement></dataSetElement><dataSetElement><dataElement id="GPtGOh8PAlK"><displayName>Malaria confirmed_Death</displayName><valueType>NUMBER</valueType><categoryCombo id="ygwDvwJSrQe"><categoryOptionCombos><categoryOptionCombo name="20yrs and above" id="aHaDmg73rhA"><categoryOptions><categoryOption name="20yrs and above"><categories><category name="Obstetric age group"/></categories></categoryOption></categoryOptions></categoryOptionCombo><categoryOptionCombo name="Under 20yrs" id="n0DeQmJ9EVJ"><categoryOptions><categoryOption name="Under 20yrs"><categories><category name="Obstetric age group"/></categories></categoryOption></categoryOptions></categoryOptionCombo></categoryOptionCombos></categoryCombo></dataElement></dataSetElement><dataSetElement><dataElement id="wRUJGPh9tuz"><displayName>Births live</displayName><valueType>NUMBER</valueType><categoryCombo id="e1sXdbpUsU7"><categoryOptionCombos><categoryOptionCombo name="default" id="BNTdWBe0N1F"><categoryOptions><categoryOption name="default"><categories><category name="default"/></categories></categoryOption></categoryOptions></categoryOptionCombo></categoryOptionCombos></categoryCombo></dataElement></dataSetElement><dataSetElement><dataElement id="J65OC46zmax"><displayName>Newborns checked for danger signs in postpartum ward within 24 hours_if mother admitted</displayName><valueType>NUMBER</valueType><categoryCombo id="e1sXdbpUsU7"><categoryOptionCombos><categoryOptionCombo name="default" id="BNTdWBe0N1F"><categoryOptions><categoryOption name="default"><categories><category name="default"/></categories></categoryOption></categoryOptions></categoryOptionCombo></categoryOptionCombos></categoryCombo></dataElement></dataSetElement><dataSetElement><dataElement id="Ggt7SxZTo7u"><displayName>Newborns breastfed within 1 hour of delivery</displayName><valueType>NUMBER</valueType><categoryCombo id="e1sXdbpUsU7"><categoryOptionCombos><categoryOptionCombo name="default" id="BNTdWBe0N1F"><categoryOptions><categoryOption name="default"><categories><category name="default"/></categories></categoryOption></categoryOptions></categoryOptionCombo></categoryOptionCombos></categoryCombo></dataElement></dataSetElement><dataSetElement><dataElement id="GN5PrX6drdc"><displayName>Uterine rupture or tear_Hosp</displayName><valueType>NUMBER</valueType><categoryCombo id="ygwDvwJSrQe"><categoryOptionCombos><categoryOptionCombo name="20yrs and above" id="aHaDmg73rhA"><categoryOptions><categoryOption name="20yrs and above"><categories><category name="Obstetric age group"/></categories></categoryOption></categoryOptions></categoryOptionCombo><categoryOptionCombo name="Under 20yrs" id="n0DeQmJ9EVJ"><categoryOptions><categoryOption name="Under 20yrs"><categories><category name="Obstetric age group"/></categories></categoryOption></categoryOptions></categoryOptionCombo></categoryOptionCombos></categoryCombo></dataElement></dataSetElement><dataSetElement><dataElement id="jIOFeDsby8k"><displayName>Ectopic pregnancy_OPDNC</displayName><valueType>NUMBER</valueType><categoryCombo id="ygwDvwJSrQe"><categoryOptionCombos><categoryOptionCombo name="20yrs and above" id="aHaDmg73rhA"><categoryOptions><categoryOption name="20yrs and above"><categories><category name="Obstetric age group"/></categories></categoryOption></categoryOptions></categoryOptionCombo><categoryOptionCombo name="Under 20yrs" id="n0DeQmJ9EVJ"><categoryOptions><categoryOption name="Under 20yrs"><categories><category name="Obstetric age group"/></categories></categoryOption></categoryOptions></categoryOptionCombo></categoryOptionCombos></categoryCombo></dataElement></dataSetElement><dataSetElement><dataElement id="g3ZyNngW7lu"><displayName>Fistula_vesico vaginal or rectal_Hospitalised</displayName><valueType>NUMBER</valueType><categoryCombo id="ygwDvwJSrQe"><categoryOptionCombos><categoryOptionCombo name="20yrs and above" id="aHaDmg73rhA"><categoryOptions><categoryOption name="20yrs and above"><categories><category name="Obstetric age group"/></categories></categoryOption></categoryOptions></categoryOptionCombo><categoryOptionCombo name="Under 20yrs" id="n0DeQmJ9EVJ"><categoryOptions><categoryOption name="Under 20yrs"><categories><category name="Obstetric age group"/></categories></categoryOption></categoryOptions></categoryOptionCombo></categoryOptionCombos></categoryCombo></dataElement></dataSetElement><dataSetElement><dataElement id="kNdeno5VPz4"><displayName>Women placed under observation for 72 hours or more</displayName><valueType>NUMBER</valueType><categoryCombo id="e1sXdbpUsU7"><categoryOptionCombos><categoryOptionCombo name="default" id="BNTdWBe0N1F"><categoryOptions><categoryOption name="default"><categories><category name="default"/></categories></categoryOption></categoryOptions></categoryOptionCombo></categoryOptionCombos></categoryCombo></dataElement></dataSetElement><dataSetElement><dataElement id="gdvvGl464OK"><displayName>Still births fresh_>22 weeks or >500 grams</displayName><valueType>NUMBER</valueType><categoryCombo id="e1sXdbpUsU7"><categoryOptionCombos><categoryOptionCombo name="default" id="BNTdWBe0N1F"><categoryOptions><categoryOption name="default"><categories><category name="default"/></categories></categoryOption></categoryOptions></categoryOptionCombo></categoryOptionCombos></categoryCombo></dataElement></dataSetElement><dataSetElement><dataElement id="kml87EMeCHH"><displayName>Deliveries 16 to 19 years</displayName><valueType>NUMBER</valueType><categoryCombo id="e1sXdbpUsU7"><categoryOptionCombos><categoryOptionCombo name="default" id="BNTdWBe0N1F"><categoryOptions><categoryOption name="default"><categories><category name="default"/></categories></categoryOption></categoryOptions></categoryOptionCombo></categoryOptionCombos></categoryCombo></dataElement></dataSetElement><dataSetElement><dataElement id="Xh9pymy5g2B"><displayName>Obstetrical Complication Other_Death</displayName><valueType>NUMBER</valueType><categoryCombo id="ygwDvwJSrQe"><categoryOptionCombos><categoryOptionCombo name="20yrs and above" id="aHaDmg73rhA"><categoryOptions><categoryOption name="20yrs and above"><categories><category name="Obstetric age group"/></categories></categoryOption></categoryOptions></categoryOptionCombo><categoryOptionCombo name="Under 20yrs" id="n0DeQmJ9EVJ"><categoryOptions><categoryOption name="Under 20yrs"><categories><category name="Obstetric age group"/></categories></categoryOption></categoryOptions></categoryOptionCombo></categoryOptionCombos></categoryCombo></dataElement></dataSetElement><dataSetElement><dataElement id="mT8zF8qImG1"><displayName>Birth trauma to infant</displayName><valueType>NUMBER</valueType><categoryCombo id="e1sXdbpUsU7"><categoryOptionCombos><categoryOptionCombo name="default" id="BNTdWBe0N1F"><categoryOptions><categoryOption name="default"><categories><category name="default"/></categories></categoryOption></categoryOptions></categoryOptionCombo></categoryOptionCombos></categoryCombo></dataElement></dataSetElement><dataSetElement><dataElement id="LTe1RxQAZJf"><displayName>Pre_eclamplsia cases receiveing magnesium sulfate</displayName><valueType>NUMBER</valueType><categoryCombo id="e1sXdbpUsU7"><categoryOptionCombos><categoryOptionCombo name="default" id="BNTdWBe0N1F"><categoryOptions><categoryOption name="default"><categories><category name="default"/></categories></categoryOption></categoryOptions></categoryOptionCombo></categoryOptionCombos></categoryCombo></dataElement></dataSetElement><dataSetElement><dataElement id="QaqSREHqTnY"><displayName>Threat of premature delivery_Hosp</displayName><valueType>NUMBER</valueType><categoryCombo id="ygwDvwJSrQe"><categoryOptionCombos><categoryOptionCombo name="20yrs and above" id="aHaDmg73rhA"><categoryOptions><categoryOption name="20yrs and above"><categories><category name="Obstetric age group"/></categories></categoryOption></categoryOptions></categoryOptionCombo><categoryOptionCombo name="Under 20yrs" id="n0DeQmJ9EVJ"><categoryOptions><categoryOption name="Under 20yrs"><categories><category name="Obstetric age group"/></categories></categoryOption></categoryOptions></categoryOptionCombo></categoryOptionCombos></categoryCombo></dataElement></dataSetElement><dataSetElement><dataElement id="SOdb3pVVYl1"><displayName>Manual vacuum aspiration_Post-Abortion Care</displayName><valueType>NUMBER</valueType><categoryCombo id="e1sXdbpUsU7"><categoryOptionCombos><categoryOptionCombo name="default" id="BNTdWBe0N1F"><categoryOptions><categoryOption name="default"><categories><category name="default"/></categories></categoryOption></categoryOptions></categoryOptionCombo></categoryOptionCombos></categoryCombo></dataElement></dataSetElement><dataSetElement><dataElement id="fICuyReInRd"><displayName>Women referred for emergency care to higher levels</displayName><valueType>NUMBER</valueType><categoryCombo id="e1sXdbpUsU7"><categoryOptionCombos><categoryOptionCombo name="default" id="BNTdWBe0N1F"><categoryOptions><categoryOption name="default"><categories><category name="default"/></categories></categoryOption></categoryOptions></categoryOptionCombo></categoryOptionCombos></categoryCombo></dataElement></dataSetElement><dataSetElement><dataElement id="WyxyUTZOhKo"><displayName>Abortions_symptoms suggesting induced abortionOPDNC</displayName><valueType>NUMBER</valueType><categoryCombo id="ygwDvwJSrQe"><categoryOptionCombos><categoryOptionCombo name="20yrs and above" id="aHaDmg73rhA"><categoryOptions><categoryOption name="20yrs and above"><categories><category name="Obstetric age group"/></categories></categoryOption></categoryOptions></categoryOptionCombo><categoryOptionCombo name="Under 20yrs" id="n0DeQmJ9EVJ"><categoryOptions><categoryOption name="Under 20yrs"><categories><category name="Obstetric age group"/></categories></categoryOption></categoryOptions></categoryOptionCombo></categoryOptionCombos></categoryCombo></dataElement></dataSetElement><dataSetElement><dataElement id="o84exadtl82"><displayName>Deliveries referred to higher level</displayName><valueType>NUMBER</valueType><categoryCombo id="e1sXdbpUsU7"><categoryOptionCombos><categoryOptionCombo name="default" id="BNTdWBe0N1F"><categoryOptions><categoryOption name="default"><categories><category name="default"/></categories></categoryOption></categoryOptions></categoryOptionCombo></categoryOptionCombos></categoryCombo></dataElement></dataSetElement><dataSetElement><dataElement id="Ev89lZnQOr3"><displayName>Obstetrical complications other_Deaths_obs</displayName><valueType>NUMBER</valueType><categoryCombo id="ygwDvwJSrQe"><categoryOptionCombos><categoryOptionCombo name="20yrs and above" id="aHaDmg73rhA"><categoryOptions><categoryOption name="20yrs and above"><categories><category name="Obstetric age group"/></categories></categoryOption></categoryOptions></categoryOptionCombo><categoryOptionCombo name="Under 20yrs" id="n0DeQmJ9EVJ"><categoryOptions><categoryOption name="Under 20yrs"><categories><category name="Obstetric age group"/></categories></categoryOption></categoryOptions></categoryOptionCombo></categoryOptionCombos></categoryCombo></dataElement></dataSetElement><dataSetElement><dataElement id="UZ7hsIQ90cy"><displayName>Intravenus Anti-hypertensives</displayName><valueType>NUMBER</valueType><categoryCombo id="e1sXdbpUsU7"><categoryOptionCombos><categoryOptionCombo name="default" id="BNTdWBe0N1F"><categoryOptions><categoryOption name="default"><categories><category name="default"/></categories></categoryOption></categoryOptions></categoryOptionCombo></categoryOptionCombos></categoryCombo></dataElement></dataSetElement><dataSetElement><dataElement id="THHOxNJE8aO"><displayName>Miscarriages_spontaneous abortions_OPDNC</displayName><valueType>NUMBER</valueType><categoryCombo id="ygwDvwJSrQe"><categoryOptionCombos><categoryOptionCombo name="20yrs and above" id="aHaDmg73rhA"><categoryOptions><categoryOption name="20yrs and above"><categories><category name="Obstetric age group"/></categories></categoryOption></categoryOptions></categoryOptionCombo><categoryOptionCombo name="Under 20yrs" id="n0DeQmJ9EVJ"><categoryOptions><categoryOption name="Under 20yrs"><categories><category name="Obstetric age group"/></categories></categoryOption></categoryOptions></categoryOptionCombo></categoryOptionCombos></categoryCombo></dataElement></dataSetElement><dataSetElement><dataElement id="chgpQyAQZMM"><displayName>Prolonged or Obstructed labor_Hosp</displayName><valueType>NUMBER</valueType><categoryCombo id="ygwDvwJSrQe"><categoryOptionCombos><categoryOptionCombo name="20yrs and above" id="aHaDmg73rhA"><categoryOptions><categoryOption name="20yrs and above"><categories><category name="Obstetric age group"/></categories></categoryOption></categoryOptions></categoryOptionCombo><categoryOptionCombo name="Under 20yrs" id="n0DeQmJ9EVJ"><categoryOptions><categoryOption name="Under 20yrs"><categories><category name="Obstetric age group"/></categories></categoryOption></categoryOptions></categoryOptionCombo></categoryOptionCombos></categoryCombo></dataElement></dataSetElement><dataSetElement><dataElement id="Owj0rWdbDlP"><displayName>Ectopic pregnancy_Deaths</displayName><valueType>NUMBER</valueType><categoryCombo id="ygwDvwJSrQe"><categoryOptionCombos><categoryOptionCombo name="20yrs and above" id="aHaDmg73rhA"><categoryOptions><categoryOption name="20yrs and above"><categories><category name="Obstetric age group"/></categories></categoryOption></categoryOptions></categoryOptionCombo><categoryOptionCombo name="Under 20yrs" id="n0DeQmJ9EVJ"><categoryOptions><categoryOption name="Under 20yrs"><categories><category name="Obstetric age group"/></categories></categoryOption></categoryOptions></categoryOptionCombo></categoryOptionCombos></categoryCombo></dataElement></dataSetElement><dataSetElement><dataElement id="PTnX2DrEtR4"><displayName>Antepartum Haemorrhage_OPDNC</displayName><valueType>NUMBER</valueType><categoryCombo id="ygwDvwJSrQe"><categoryOptionCombos><categoryOptionCombo name="20yrs and above" id="aHaDmg73rhA"><categoryOptions><categoryOption name="20yrs and above"><categories><category name="Obstetric age group"/></categories></categoryOption></categoryOptions></categoryOptionCombo><categoryOptionCombo name="Under 20yrs" id="n0DeQmJ9EVJ"><categoryOptions><categoryOption name="Under 20yrs"><categories><category name="Obstetric age group"/></categories></categoryOption></categoryOptions></categoryOptionCombo></categoryOptionCombos></categoryCombo></dataElement></dataSetElement><dataSetElement><dataElement id="GYqGg7giekC"><displayName>Sepsis_Postpartum infection_Hosp</displayName><valueType>NUMBER</valueType><categoryCombo id="ygwDvwJSrQe"><categoryOptionCombos><categoryOptionCombo name="20yrs and above" id="aHaDmg73rhA"><categoryOptions><categoryOption name="20yrs and above"><categories><category name="Obstetric age group"/></categories></categoryOption></categoryOptions></categoryOptionCombo><categoryOptionCombo name="Under 20yrs" id="n0DeQmJ9EVJ"><categoryOptions><categoryOption name="Under 20yrs"><categories><category name="Obstetric age group"/></categories></categoryOption></categoryOptions></categoryOptionCombo></categoryOptionCombos></categoryCombo></dataElement></dataSetElement><dataSetElement><dataElement id="krWvxbmJ8RK"><displayName>Birth weight &lt;2.5 kg _alive not premature</displayName><valueType>NUMBER</valueType><categoryCombo id="e1sXdbpUsU7"><categoryOptionCombos><categoryOptionCombo name="default" id="BNTdWBe0N1F"><categoryOptions><categoryOption name="default"><categories><category name="default"/></categories></categoryOption></categoryOptions></categoryOptionCombo></categoryOptionCombos></categoryCombo></dataElement></dataSetElement><dataSetElement><dataElement id="ajIhG9C0unm"><displayName>Malaria simple in pregnancyHosp_Obs</displayName><valueType>NUMBER</valueType><categoryCombo id="ygwDvwJSrQe"><categoryOptionCombos><categoryOptionCombo name="20yrs and above" id="aHaDmg73rhA"><categoryOptions><categoryOption name="20yrs and above"><categories><category name="Obstetric age group"/></categories></categoryOption></categoryOptions></categoryOptionCombo><categoryOptionCombo name="Under 20yrs" id="n0DeQmJ9EVJ"><categoryOptions><categoryOption name="Under 20yrs"><categories><category name="Obstetric age group"/></categories></categoryOption></categoryOptions></categoryOptionCombo></categoryOptionCombos></categoryCombo></dataElement></dataSetElement><dataSetElement><dataElement id="pJEqN7HsoT9"><displayName>Antepartum Haemorrhage_Hosp</displayName><valueType>NUMBER</valueType><categoryCombo id="ygwDvwJSrQe"><categoryOptionCombos><categoryOptionCombo name="20yrs and above" id="aHaDmg73rhA"><categoryOptions><categoryOption name="20yrs and above"><categories><category name="Obstetric age group"/></categories></categoryOption></categoryOptions></categoryOptionCombo><categoryOptionCombo name="Under 20yrs" id="n0DeQmJ9EVJ"><categoryOptions><categoryOption name="Under 20yrs"><categories><category name="Obstetric age group"/></categories></categoryOption></categoryOptions></categoryOptionCombo></categoryOptionCombos></categoryCombo></dataElement></dataSetElement><dataSetElement><dataElement id="BxhmCCUDJ54"><displayName>Newborns checked for danger signs in postpartum ward before discharge_if mother admitted</displayName><valueType>NUMBER</valueType><categoryCombo id="e1sXdbpUsU7"><categoryOptionCombos><categoryOptionCombo name="default" id="BNTdWBe0N1F"><categoryOptions><categoryOption name="default"><categories><category name="default"/></categories></categoryOption></categoryOptions></categoryOptionCombo></categoryOptionCombos></categoryCombo></dataElement></dataSetElement><dataSetElement><dataElement id="fbhHP3u7m7F"><displayName>Still births macerated_>22 weeks or >500 grams</displayName><valueType>NUMBER</valueType><categoryCombo id="e1sXdbpUsU7"><categoryOptionCombos><categoryOptionCombo name="default" id="BNTdWBe0N1F"><categoryOptions><categoryOption name="default"><categories><category name="default"/></categories></categoryOption></categoryOptions></categoryOptionCombo></categoryOptionCombos></categoryCombo></dataElement></dataSetElement><dataSetElement><dataElement id="g8Lf300p9T3"><displayName>Post-partum hemorrhage_OPDNC</displayName><valueType>NUMBER</valueType><categoryCombo id="ygwDvwJSrQe"><categoryOptionCombos><categoryOptionCombo name="20yrs and above" id="aHaDmg73rhA"><categoryOptions><categoryOption name="20yrs and above"><categories><category name="Obstetric age group"/></categories></categoryOption></categoryOptions></categoryOptionCombo><categoryOptionCombo name="Under 20yrs" id="n0DeQmJ9EVJ"><categoryOptions><categoryOption name="Under 20yrs"><categories><category name="Obstetric age group"/></categories></categoryOption></categoryOptions></categoryOptionCombo></categoryOptionCombos></categoryCombo></dataElement></dataSetElement><dataSetElement><dataElement id="GPcZ2GRyy5s"><displayName>Deliveries 35 years and above</displayName><valueType>NUMBER</valueType><categoryCombo id="e1sXdbpUsU7"><categoryOptionCombos><categoryOptionCombo name="default" id="BNTdWBe0N1F"><categoryOptions><categoryOption name="default"><categories><category name="default"/></categories></categoryOption></categoryOptions></categoryOptionCombo></categoryOptionCombos></categoryCombo></dataElement></dataSetElement><dataSetElement><dataElement id="Rv2FX68XQHK"><displayName>Foetal Distress_OPDNC</displayName><valueType>NUMBER</valueType><categoryCombo id="ygwDvwJSrQe"><categoryOptionCombos><categoryOptionCombo name="20yrs and above" id="aHaDmg73rhA"><categoryOptions><categoryOption name="20yrs and above"><categories><category name="Obstetric age group"/></categories></categoryOption></categoryOptions></categoryOptionCombo><categoryOptionCombo name="Under 20yrs" id="n0DeQmJ9EVJ"><categoryOptions><categoryOption name="Under 20yrs"><categories><category name="Obstetric age group"/></categories></categoryOption></categoryOptions></categoryOptionCombo></categoryOptionCombos></categoryCombo></dataElement></dataSetElement><dataSetElement><dataElement id="TWmX6JS19hO"><displayName>Deliveries_Total</displayName><valueType>NUMBER</valueType><categoryCombo id="e1sXdbpUsU7"><categoryOptionCombos><categoryOptionCombo name="default" id="BNTdWBe0N1F"><categoryOptions><categoryOption name="default"><categories><category name="default"/></categories></categoryOption></categoryOptions></categoryOptionCombo></categoryOptionCombos></categoryCombo></dataElement></dataSetElement><dataSetElement><dataElement id="VfzC8s6TUrs"><displayName>Maternal deaths during delivery_subset of all deaths in table VIII.A above</displayName><valueType>NUMBER</valueType><categoryCombo id="e1sXdbpUsU7"><categoryOptionCombos><categoryOptionCombo name="default" id="BNTdWBe0N1F"><categoryOptions><categoryOption name="default"><categories><category name="default"/></categories></categoryOption></categoryOptions></categoryOptionCombo></categoryOptionCombos></categoryCombo></dataElement></dataSetElement><dataSetElement><dataElement id="wa5HBNvPFr6"><displayName>Anemia Severe _&lt;7gm/dl_Hospitalisation</displayName><valueType>NUMBER</valueType><categoryCombo id="ygwDvwJSrQe"><categoryOptionCombos><categoryOptionCombo name="20yrs and above" id="aHaDmg73rhA"><categoryOptions><categoryOption name="20yrs and above"><categories><category name="Obstetric age group"/></categories></categoryOption></categoryOptions></categoryOptionCombo><categoryOptionCombo name="Under 20yrs" id="n0DeQmJ9EVJ"><categoryOptions><categoryOption name="Under 20yrs"><categories><category name="Obstetric age group"/></categories></categoryOption></categoryOptions></categoryOptionCombo></categoryOptionCombos></categoryCombo></dataElement></dataSetElement><dataSetElement><dataElement id="EcgQ17EawEC"><displayName>Multiple Pregnancies women who delivered_twins_triplets_etc</displayName><valueType>NUMBER</valueType><categoryCombo id="e1sXdbpUsU7"><categoryOptionCombos><categoryOptionCombo name="default" id="BNTdWBe0N1F"><categoryOptions><categoryOption name="default"><categories><category name="default"/></categories></categoryOption></categoryOptions></categoryOptionCombo></categoryOptionCombos></categoryCombo></dataElement></dataSetElement><dataSetElement><dataElement id="JBCRfInSOPs"><displayName>Newborns referred to higher level</displayName><valueType>NUMBER</valueType><categoryCombo id="e1sXdbpUsU7"><categoryOptionCombos><categoryOptionCombo name="default" id="BNTdWBe0N1F"><categoryOptions><categoryOption name="default"><categories><category name="default"/></categories></categoryOption></categoryOptions></categoryOptionCombo></categoryOptionCombos></categoryCombo></dataElement></dataSetElement><dataSetElement><dataElement id="uMvdLMFuRwO"><displayName>Uterine rupture or tear_Deaths</displayName><valueType>NUMBER</valueType><categoryCombo id="ygwDvwJSrQe"><categoryOptionCombos><categoryOptionCombo name="20yrs and above" id="aHaDmg73rhA"><categoryOptions><categoryOption name="20yrs and above"><categories><category name="Obstetric age group"/></categories></categoryOption></categoryOptions></categoryOptionCombo><categoryOptionCombo name="Under 20yrs" id="n0DeQmJ9EVJ"><categoryOptions><categoryOption name="Under 20yrs"><categories><category name="Obstetric age group"/></categories></categoryOption></categoryOptions></categoryOptionCombo></categoryOptionCombos></categoryCombo></dataElement></dataSetElement><dataSetElement><dataElement id="LQkOquYGgjU"><displayName>HIV/Opportunistic Infections_OPDNC</displayName><valueType>NUMBER</valueType><categoryCombo id="ygwDvwJSrQe"><categoryOptionCombos><categoryOptionCombo name="20yrs and above" id="aHaDmg73rhA"><categoryOptions><categoryOption name="20yrs and above"><categories><category name="Obstetric age group"/></categories></categoryOption></categoryOptions></categoryOptionCombo><categoryOptionCombo name="Under 20yrs" id="n0DeQmJ9EVJ"><categoryOptions><categoryOption name="Under 20yrs"><categories><category name="Obstetric age group"/></categories></categoryOption></categoryOptions></categoryOptionCombo></categoryOptionCombos></categoryCombo></dataElement></dataSetElement><dataSetElement><dataElement id="wFrzS94LMkF"><displayName>Threat of premature delivery_Deaths</displayName><valueType>NUMBER</valueType><categoryCombo id="ygwDvwJSrQe"><categoryOptionCombos><categoryOptionCombo name="20yrs and above" id="aHaDmg73rhA"><categoryOptions><categoryOption name="20yrs and above"><categories><category name="Obstetric age group"/></categories></categoryOption></categoryOptions></categoryOptionCombo><categoryOptionCombo name="Under 20yrs" id="n0DeQmJ9EVJ"><categoryOptions><categoryOption name="Under 20yrs"><categories><category name="Obstetric age group"/></categories></categoryOption></categoryOptions></categoryOptionCombo></categoryOptionCombos></categoryCombo></dataElement></dataSetElement></dataSetElements></dataSet>